Metadata-Version: 1.0
Name: envoy-proxy-validator
Version: 0.0.3
Summary: python compile files for envoy proxy validator
Home-page: https://sunyunqiang.com
Author: yunqiang-sun
Author-email: admin@sunyunqiang.com
License: UNKNOWN
Platform: UNKNOWN
